LICENSE
lb_health_check/__init__.py
lb_health_check/apps.py
lb_health_check/middleware.py
lb_health_check/tests.py
django_lb_health_check-1.0.1.dist-info/LICENSE
django_lb_health_check-1.0.1.dist-info/WHEEL
django_lb_health_check-1.0.1.dist-info/METADATA
django_lb_health_check-1.0.1.dist-info/RECORD
