Metadata-Version: 2.1
Name: django-lb-health-check
Version: 1.0.1
Summary: Middleware based health check for Django
Home-page: https://github.com/Hovercross/django-lb-health-check
License: MIT
Keywords: django,health,alive,check
Author: Adam Peacock
Author-email: adam@thepeacock.net
Requires-Python: >=3.6.2
Classifier: Development Status :: 4 - Beta
Classifier: Environment :: Web Environment
Classifier: Framework :: Django
Classifier: Intended Audience :: Developers
Classifier: License :: OSI Approved :: MIT License
Classifier: Operating System :: OS Independent
Classifier: Programming Language :: Python :: 3
Classifier: Programming Language :: Python :: 3.10
Classifier: Programming Language :: Python :: 3.7
Classifier: Programming Language :: Python :: 3.8
Classifier: Programming Language :: Python :: 3.9
Requires-Dist: Django (>=2.2)
Project-URL: Repository, https://github.com/Hovercross/django-lb-health-check
